neologist/__init__.py
neologist-0.0.1.dist-info/METADATA
neologist-0.0.1.dist-info/WHEEL
neologist-0.0.1.dist-info/top_level.txt
neologist-0.0.1.dist-info/RECORD
